{"paths":{"0":["dianwei3_1",0],"1":["dianwei3_attack_hit",1],"2":["dianwei3_1",1],"3":["dianwei3_1",2],"4":["dianwei3_attack_hit",2],"5":["dianwei3_attack_hit",0],"6":["dianwei3_1",3,1],"7":["dianwei3_attack_hit",3,1]},"types":["cc.Asset","cc.Texture2D","sp.SkeletonData","cc.SpriteFrame"],"uuids":["47YaN4IYhHFbxnP96/kPs9","5e478DPipMoK308hAgHOnI","7blocuABxIYKMSji4glmcQ","8c9W27En1OBLVbl2/8V0JR","a7++cpRldOyZjwLL6KP7YF","b6+ZLGuHVPKLox/5bL/HNi","adTEA0xdhGn7yrGaukMfNn","f3V1505hpDQI+0Bv9OxeuL"],"scenes":{},"redirect":[],"deps":[],"packs":{},"name":"dianwei3_1","importBase":"import","nativeBase":"native","debug":false,"isZip":false,"encrypted":false,"versions":{"import":[0,"a5f48",1,"f0473",2,"f0473",3,"1788a",4,"249cd",6,"bac15",5,"8e8d0",7,"23a28"],"native":[0,"e63ce",1,"7f72d",2,"0ba2c",3,"29779",4,"ac801",5,"60d90"]}}