{"paths":{"0":["dengshenwu_attack_hit",3],"1":["dengshenwu_skill_hit",3],"2":["dengshenwu_skill_hit",0],"3":["dengshenwu_attack_hit",0],"4":["dengshenwu_skill_hit",2],"5":["dengshenwu_attack_hit",2],"6":["dengshenwu_skill_loop",3],"7":["dengshenwu",0],"8":["dengshenwu_skill_loop",2],"9":["dengshenwu",2],"10":["dengshenwu",3],"11":["dengshenwu_skill_loop",0],"12":["dengshenwu_skill_hit",1,1],"13":["dengshenwu",1,1],"14":["dengshenwu_attack_hit",1,1],"15":["dengshenwu_skill_loop",1,1]},"types":["cc.Asset","cc.SpriteFrame","cc.Texture2D","sp.SkeletonData"],"uuids":["05bziIdsFIk7wcTiuXbvg2","3dY7jtZlBJ1LFZgJngLNZU","56g3eXNwJPbY81mWfX3SpD","5akJ21nRlEM5g5I+VQ+Myx","69ctRdSFJGuJ7eOu1LhlCv","86ZUdgU8lGG5mjbDwcVzyj","9dgNeKCl5ANKWH4sSAt90d","a5wnp1/kVELb+1VJvZRJb+","a7ZgsCHrZNNKl0+XsVC9SR","b4yl5krypLvqzlinzJDlcB","c85pw1LfJPjK7OcnDNW0fS","e8lj+GDWlJCaEOqC9La6UP","04te4p+7pC6pJEZMyoXIMw","acl0LGk29OTq9A0rWQb8sO","b6qQ7nbitKQIqYX/QwBMFU","caZGdzKKlAg5czrnlm+HSi"],"scenes":{},"redirect":[],"deps":[],"packs":{},"name":"dengshenwu","importBase":"import","nativeBase":"native","debug":false,"isZip":false,"encrypted":false,"versions":{"import":[12,"a62d8",0,"7a9b4",1,"26558",2,"705f1",3,"70d08",4,"f0473",5,"f0473",6,"91c69",7,"d6076",8,"f0473",13,"501c3",9,"f0473",14,"e76d5",10,"aaeb0",15,"d633d",11,"398ab"],"native":[0,"dec8d",1,"c885f",2,"de05b",3,"0ff6f",4,"18c16",5,"fe1fc",6,"66b4c",7,"4a7ac",8,"26754",9,"96ee2",10,"0d1aa",11,"556d8"]}}