{"paths":{"0":["sjhd_chest",0],"1":["sjhd_chest",2],"2":["sjhd_chest",3],"3":["sjhd_chest",1,1]},"types":["cc.Texture2D","cc.SpriteFrame","sp.SkeletonData","cc.Asset"],"uuids":["32dr3UP9ZA3ZAQjSz2QNCo","8c8ZAhvEhIh51/SIAD4Xuq","eadrvQ+bRJILqUHiU9RoIL","74y4Tuz6JLhJslbN9qkv25"],"scenes":{},"redirect":[],"deps":[],"packs":{},"name":"sjhd_chest","importBase":"import","nativeBase":"native","debug":false,"isZip":false,"encrypted":false,"versions":{"import":[0,"f0473",3,"77312",1,"478d8",2,"4ac23"],"native":[0,"eba99",1,"4e345",2,"73ee6"]}}