{"paths":{"0":["ygbh_rg_jiantou",2],"1":["ui_festival_rogue_atlas0",0],"2":["ygbh_rg_ygbh2",0],"3":["ygbh_rg_jiantou",0],"4":["dsqq_rg_swk",2],"5":["ui_festival_rogue_atlas_ntupav",0],"6":["ygbh_js_tzsb",3],"7":["dsqq_rg_fly",0],"8":["ygbh_rg_xuanzhong",2],"9":["ygbh_rg_ygbh2",2],"10":["ygbh_rg_pubu",3],"11":["caoren4",0],"12":["ui_festival_rogue",4],"13":["caoren",0],"14":["ygbh_rg_xuanzhong",3],"15":["ygbh_rg_putao",0],"16":["ygbh_rg_jiantou",3],"17":["dsqq_rg_xg_1",0],"18":["dsqq_rg_xinniang",2],"19":["dsqq_rg_fly",3],"20":["dsqq_rg_xg_3",2],"21":["tbhdqx_rg_xxy",2],"22":["dsqq_rg_fly",2],"23":["caoren6",2],"24":["ygbh_rg_putao",2],"25":["dsqq_rg_xg_2",2],"26":["tbhdqx_rg_xxy",0],"27":["ui_festival_rogue_atlas_ntupb7",0],"28":["ygbh_js_tzcg",3],"29":["dsqq_rg_swk",3],"30":["tbhdqx_rg_qx",0],"31":["ygbh_rg_pubu",0],"32":["dsqq_rg_swk",0],"33":["dsqq_rg_xg_2",0],"34":["caoren4",3],"35":["ygbh_js_tzcg",0],"36":["dsqq_rg_xg_3",3],"37":["ygbh_rg_zzb",2],"38":["ygbh_js_tzcg",2],"39":["tbhdqx_rg_xxy",3],"40":["dsqq_rg_xg_1",3],"41":["ygbh_rg_ygbh",0],"42":["ygbh_rg_pubu",2],"43":["ygbh_rg_zzb",3],"44":["ygbh_rg_putao",3],"45":["tbhdqx_rg_qx",3],"46":["dsqq_rg_xg_3",0],"47":["ygbh_rg_zzb",0],"48":["tbhdqx_rg_qx",2],"49":["caoren6",0],"50":["caoren",2],"51":["ui_festival_rogue_atlas_ntupb3",0],"52":["ygbh_rg_ygbh2",3],"53":["dsqq_rg_xg_2",3],"54":["ygbh_rg_xuanzhong",0],"55":["ygbh_js_tzsb",2],"56":["dsqq_rg_xinniang",3],"57":["ygbh_rg_ygbh",3],"58":["caoren",3],"59":["caoren6",3],"60":["dsqq_rg_xg_1",2],"61":["ygbh_js_tzsb",0],"62":["ygbh_rg_ygbh",2],"63":["caoren4",2],"64":["dsqq_rg_xinniang",0],"65":["ygbh_js_tzcg",1,1],"66":["ui_festival_rogue_atlas_ntupb7",1,1],"67":["ygbh_rg_ygbh2",1,1],"68":["ygbh_rg_zzb",1,1],"69":["caoren4",1,1],"70":["ygbh_js_tzsb",1,1],"71":["dsqq_rg_xg_2",1,1],"72":["ui_festival_rogue_atlas0",1,1],"73":["dsqq_rg_swk",1,1],"74":["caoren6",1,1],"75":["tbhdqx_rg_xxy",1,1],"76":["ygbh_rg_ygbh",1,1],"77":["ui_festival_rogue_atlas_ntupb3",1,1],"78":["ygbh_rg_pubu",1,1],"79":["ygbh_rg_xuanzhong",1,1],"80":["dsqq_rg_fly",1,1],"81":["caoren",1,1],"82":["tbhdqx_rg_qx",1,1],"83":["dsqq_rg_xinniang",1,1],"84":["ygbh_rg_jiantou",1,1],"85":["ygbh_rg_putao",1,1],"86":["dsqq_rg_xg_3",1,1],"87":["dsqq_rg_xg_1",1,1],"88":["ui_festival_rogue_atlas_ntupav",1,1]},"types":["cc.Texture2D","cc.SpriteFrame","sp.SkeletonData","cc.Asset","cc.BufferAsset"],"uuids":["08i9TMS6xIa6xunQrftg/K","0aR6rl+n1ON6+YhZyaNUTq","0atNfT84tG351Z/U6CZXYr","22GnU4yxpCvL4r1kmLD1gJ","24HBTT2flICZOljGIIrcKE","24YEca6gdK0IIzu/it+RN0","24yZgsm9xBTJaRalLmzvOj","2ahA9TE4NAkr1D6Tz6YmSe","2cs4bbx7ZARato/kGMkrzF","2dRuB79zNHZIbtheq63+YU","2f3iX+x/FLDZVvikPvHlUh","30SUn1LRRMpockSLYcJb2V","318JCTqaxPqJ99gCId/yR0","32v4rVPJRPlbEm0dGfEE+y","33Btc7rJJF8K7CiJaxsaTV","36Kqoj7E1GpZrMjqHWp+ds","3eZXc6xDtHoLXrVEgQkemE","41/nVnXKdKAJLrbkPviAFj","44XVa3DUpI05h1GscZP+/O","49VQCXSJdKLrZa2YGJX47L","49nqkpNbpBBp0D3omPxdA2","4bpddP9kpM/6f5JqTIj6up","4btbZCr8RIOY8M2IHa4FGp","4dFgkrsH1G+p5Xw8CPfQ1N","4fyQzqjI1CapfK2KvQowBC","52B3jotdFPPoVPPvlZKxEk","53/Nb7dRdDConwB6fn/r/J","54Hb8Sb+JMB6+pEoLQzFPO","54NCJ75ndKXJ/hArASIngN","59eCacLUtEM7PjzN7PziWL","5eeOOieVVLwY9mYE43BYbF","680iMfI+BKrKoFPvttii7Y","69/HPDbYFP6oTtpi/2lPS0","6eabo7RPpJuINVHAl+t/iL","70vo38shtEXJGh8EroxWEK","71ynnVzldJJ4q8zhH8Nzbi","82GcHka9FFEKm9z38uiZU8","84d6NzbQBGqL2WwQnfFWWp","8b7QN6IDZPpZNXBg7aUBjU","94W3sQt3RE0rPjlr9Y8EMv","9atVXhJnRGT4hPeFvnBoH/","9cAK9moHlMVJpDLnIwHmkT","9ejg3jX8NFS58IOWoZiZif","a8H1UvuEtEGocWGky1r68E","b1r80RSfZFrq3BdZjWYOtN","baC7fWu6pBy6u/TXORABoY","bdXy1Reh5C9o+xH37z+arF","c0/r7Rui5NPZseakLBVwMI","c158YLG2VFZq8B6Mmm0/MS","c6fHKu2OdNhr+48ewuF30p","cbftBkVj9JuK0U+gcxFnUL","cel+n52BpHcbpO+qrIru3E","d6d5F12j1LxbcUyjI6DdYK","d7bn9NDRdMvLS7CjeH27L5","d9c0miFf1JYJsxSBuhNUB0","e04iVTu+tLqJuAysRx3dFS","e5c62ZKkNG7ZqzoFg7UDsQ","e8TsoXnutCEb2uWZcGfbzw","e9mE2JUihN77H0vw4GRm/n","eaaBRNe05LTqtQja2MxWBD","ebAzm+OUFJLLcAyJUI+JN8","eeLyjTT+5KSJ1e3T+ghS6U","f8OmfZ/MlMtrJS3JZiRQbI","fbCm8vn95IpqtkTgLcD3D4","feKoQm6TBLm6OHdKZayZO6","04y9AK2cZIib24B2leGQP6","0dTS0+EYJPKqFk9U9jqW7y","17OahTBqlMjqfEKC1TWLyi","3d46emQAtKBKtFyGii3K6j","41pqBdB1NCvbYz8Hu4hHnL","47RalFv+9IWb6exLDkzgSm","48PSxPCRxN+qOt9Gry+EGo","4dQy/x0Y9Nvr7jKfOLmxrh","50SJEkXxZDQLBRWwmN52RN","79wm/q5fZPa7N8+pjjTC0b","7bdhBPBkpCDopvaa09De9/","7eRLsmDa1AhoXz+HORXcRa","90QUuxti9ImK2UNQf9UiDR","a2SU/Nq41D943fIMMTZ118","b4s0WWEVhG/YTr/BHM75G8","b7YpKRSu1AeKYm4Ir8vaj2","bf73u44dhE5oEgvXt6YFAA","cbz6DlKEdAV76fRSBoNULZ","ccZfrBS9FGKaUqeG0wiDo9","d9PZ9IS1dLebH3zsWG8eIv","dccCUalFxPFZ8M7cvdGX/+","e5Jp+OLPhD+7iCZY9QW7ny","ecEM179BFPKLpo2PkCUcEl","fcXZuUaqtAZIwrjhhdy4CV"],"scenes":{},"redirect":[],"deps":[],"packs":{},"name":"ui_festival_rogue","importBase":"import","nativeBase":"native","debug":false,"isZip":false,"encrypted":false,"versions":{"import":[65,"6fb72",0,"00cbd",1,"f0473",2,"f0473",66,"7c813",67,"d9628",3,"f0473",4,"d5141",5,"f0473",6,"3ab78",7,"f0473",8,"9e824",9,"49487",10,"e0bcd",11,"f0473",12,"a0aa6",13,"f0473",14,"5d3e2",15,"f0473",68,"96a14",16,"5d457",69,"ef27d",17,"f0473",18,"54d59",70,"6b93b",71,"33747",19,"62a30",20,"6ea75",21,"975f5",22,"d0683",23,"28fe8",72,"a952b",24,"5bcef",73,"3270d",25,"9e193",26,"f0473",27,"f0473",28,"d93d3",29,"e8fe8",30,"f0473",31,"f0473",32,"f0473",33,"f0473",34,"a4d14",35,"f0473",74,"62b8f",75,"c83d6",76,"4a15b",36,"eaae1",37,"2af8e",38,"7110b",77,"01498",39,"61c4d",40,"ca923",41,"f0473",42,"bcb63",78,"a474b",43,"7e414",44,"8c6c5",79,"743dd",80,"7b5d2",45,"01920",46,"f0473",81,"458b9",47,"f0473",48,"15e7f",49,"f0473",50,"ab642",82,"abec4",83,"f6f22",51,"f0473",52,"16d88",53,"5b87c",84,"a4735",54,"f0473",85,"2e010",55,"b683e",86,"df644",56,"04081",57,"8e55d",58,"6f982",59,"3b22a",60,"cad5d",87,"f81d9",61,"f0473",62,"66b7f",63,"447de",88,"8b3f9",64,"f0473"],"native":[0,"eae59",1,"a0c05",2,"57b60",3,"9dd39",4,"5fb16",5,"4ebee",6,"92c12",7,"0b763",8,"63490",9,"f18d7",10,"dcc69",11,"722ab",12,"4910b",13,"e72dc",14,"41484",15,"fd136",16,"79cc7",17,"1040b",18,"34431",19,"84530",20,"66b9f",21,"ba5e6",22,"f9dc9",23,"673d6",24,"07f9e",25,"77b16",26,"c23b1",27,"4e879",28,"8cca4",29,"384ab",30,"9ff8e",31,"739a8",32,"3801a",33,"e34bc",34,"dcfdc",35,"1168b",36,"28b01",37,"2501e",38,"b7385",39,"ce6d7",40,"8988c",41,"ccdcb",42,"771a6",43,"491c4",44,"a6681",45,"412cd",46,"63274",47,"20940",48,"e3e12",49,"0ba92",50,"55b60",51,"9b04c",52,"5c6fc",53,"d3641",54,"56f64",55,"29c75",56,"50ad8",57,"3a8c5",58,"205fa",59,"45a90",60,"3db83",61,"77476",62,"7cbd6",63,"88d22",64,"089e0"]}}