{"paths":{"0":["ls_jiaxu8",1],"1":["ls_jiaxu8",2],"2":["ls_jiaxu8",3],"3":["ls_jiaxu8",0,1]},"types":["cc.SpriteFrame","cc.Asset","sp.SkeletonData","cc.Texture2D"],"uuids":["95p6LL9AlOmphjxHOQTCWj","a8IFz5fE9Ne7KHY4md5M0o","e5HO/usDZIILm/kO5yJDEK","4dNgLNTZlCubx+tRg7XJiO"],"scenes":{},"redirect":[],"deps":[],"packs":{},"name":"ls_jiaxu8","importBase":"import","nativeBase":"native","debug":false,"isZip":false,"encrypted":false,"versions":{"import":[3,"1cf75",0,"c21f6",1,"2303e",2,"f0473"],"native":[0,"68a62",1,"da5b0",2,"8cf65"]}}