{"paths":{"0":["yuling_1109_plt",0],"1":["yuling_1109_plt",2],"2":["yuling_1109_plt",3],"3":["yuling_1109_plt",1,1]},"types":["sp.SkeletonData","cc.SpriteFrame","cc.Asset","cc.Texture2D"],"uuids":["03rs5sq4tPlaEGSqpQeIxy","8fxVTIJYJGuYzu98eYen2/","98YJsdc6tFKogqheycNDcO","7fBJFivUtOvbVCMJXdMi5G"],"scenes":{},"redirect":[],"deps":[],"packs":{},"name":"yuling_1109_plt","importBase":"import","nativeBase":"native","debug":false,"isZip":false,"encrypted":false,"versions":{"import":[0,"af08a",3,"6a68c",1,"39f7c",2,"f0473"],"native":[0,"82e88",1,"45102",2,"ddeca"]}}