{"paths":{"0":["yuling_1209",0],"1":["yuling_1209",2],"2":["yuling_1209",3],"3":["yuling_1209",1,1]},"types":["cc.Asset","cc.SpriteFrame","cc.Texture2D","sp.SkeletonData"],"uuids":["34H6M94SNACpk9OIUd4kzk","bdSVbBs9VPMI34HAoZllWf","f7JIPhGGxM9q3Y6YpV/TML","7e4nDd8gJLwIGTUYG93SHx"],"scenes":{},"redirect":[],"deps":[],"packs":{},"name":"yuling_1209","importBase":"import","nativeBase":"native","debug":false,"isZip":false,"encrypted":false,"versions":{"import":[0,"e5a34",3,"83d7f",1,"f0473",2,"1cfef"],"native":[0,"74807",1,"30d39",2,"2ef9d"]}}