{"paths":{"0":["ui_tiledMap_9_medium_atlas0",1],"1":["ui_tiledMap_9_medium_atlas0_1",1],"2":["ui_tiledMap_9_medium",0],"3":["ui_tiledMap_9_medium_atlas0_1",2,1],"4":["ui_tiledMap_9_medium_atlas0",2,1]},"types":["cc.BufferAsset","cc.Texture2D","cc.SpriteFrame"],"uuids":["0d3LkisEJL4IkRh7CwiLnc","55FidJWTNPOIhzloP3Nast","c8m1jOHMlH0I/Alzc2IlYO","15VzLwxZtI0a0RmY1t/Hka","eaKqPHSjlDKKDwH9izAgjv"],"scenes":{},"redirect":[],"deps":[],"packs":{},"name":"ui_tiledMap_9_medium","importBase":"import","nativeBase":"native","debug":false,"isZip":false,"encrypted":false,"versions":{"import":[0,"f0473",3,"9a166",1,"f0473",2,"1dbaa",4,"ef1c7"],"native":[0,"2737e",1,"0e8db",2,"88e8e"]}}