{"paths":{"0":["ssxt_mp_lusu4",0],"1":["ssxt_mp_lusu4",1],"2":["ssxt_mp_lusu4",3],"3":["ssxt_mp_lusu4",2,1]},"types":["cc.Texture2D","cc.Asset","cc.SpriteFrame","sp.SkeletonData"],"uuids":["46GR1CQtBF9ZFAxkAh2/Dq","59hiWM1VRGCajANb/Qc0Q9","beqv2nJR1BGq9Y/6a+bpl7","9e1u80N2FNcIxtqBV1NlKI"],"scenes":{},"redirect":[],"deps":[],"packs":{},"name":"ssxt_mp_lusu4","importBase":"import","nativeBase":"native","debug":false,"isZip":false,"encrypted":false,"versions":{"import":[0,"f0473",1,"08b26",3,"a6d4d",2,"043b3"],"native":[0,"e4931",1,"658ed",2,"5d006"]}}