{"paths":{"0":["ui_tiledMap_25_medium_atlas0_2",1],"1":["ui_tiledMap_25_medium_atlas0_1",1],"2":["ui_tiledMap_25_medium",0],"3":["ui_tiledMap_25_medium_atlas0",1],"4":["ui_tiledMap_25_medium_atlas0_1",2,1],"5":["ui_tiledMap_25_medium_atlas0",2,1],"6":["ui_tiledMap_25_medium_atlas0_2",2,1]},"types":["cc.BufferAsset","cc.Texture2D","cc.SpriteFrame"],"uuids":["07pDaE51ZKa6kcoQaPKiVG","18sIj3BVBA7pxmlTZ6Ph16","96QTibhLdMm7JmPFFvYdd6","d7sTGwTlxA1oj7V228svuG","36MNooY1dPdbobVL9TAnP3","e98nGpqI9HG4Wpa/Z9W/6S","ebRydCpmJK0pQ886kaDhcP"],"scenes":{},"redirect":[],"deps":[],"packs":{},"name":"ui_tiledMap_25_medium","importBase":"import","nativeBase":"native","debug":false,"isZip":false,"encrypted":false,"versions":{"import":[0,"f0473",1,"f0473",4,"80869",2,"b1709",3,"f0473",5,"7e741",6,"ab579"],"native":[0,"7f594",1,"ebcc5",2,"fe454",3,"a2b78"]}}