{"paths":{"0":["yuling_1109",1],"1":["yuling_1109",2],"2":["yuling_1109",3],"3":["yuling_1109",0,1]},"types":["cc.SpriteFrame","sp.SkeletonData","cc.Asset","cc.Texture2D"],"uuids":["0eeR0N/6pGH7nyEjlGPEdr","a4Vj2K565HuanhpePe2ERd","d1RvgmzilAZ7sALiLxwWwp","0aliqdPrtIw5Iga55VebjB"],"scenes":{},"redirect":[],"deps":[],"packs":{},"name":"pearl_yuling_1109","importBase":"import","nativeBase":"native","debug":false,"isZip":false,"encrypted":false,"versions":{"import":[3,"d2324",0,"0460e",1,"12f18",2,"f0473"],"native":[0,"d8e20",1,"c4cdb",2,"8c4ad"]}}