{"paths":{"0":["ycxsz_jiesuan_5111",0],"1":["ycxsz_jiesuan_5111",2],"2":["ycxsz_jiesuan_5111",3],"3":["ycxsz_jiesuan_5111",1,1]},"types":["sp.SkeletonData","cc.SpriteFrame","cc.Texture2D","cc.Asset"],"uuids":["28XJ6/XYpC4apt7piFbW+D","62imrvFsNI9b9hu3Mv+cH4","daZbBW3LxL6K1byklwm4bB","4aCXtCnTVN67yDr7XAi6u2"],"scenes":{},"redirect":[],"deps":[],"packs":{},"name":"ycxsz_jiesuan_5111","importBase":"import","nativeBase":"native","debug":false,"isZip":false,"encrypted":false,"versions":{"import":[0,"e3370",3,"4bcdf",1,"f0473",2,"bec09"],"native":[0,"c8144",1,"cc4c2",2,"7a8eb"]}}