{"paths":{"0":["zhaoyun_skill_hit",1],"1":["zhaoyun",1],"2":["zhaoyun",2],"3":["zhaoyun",3],"4":["zhaoyun_skill_hit",2],"5":["zhaoyun_skill_hit",3],"6":["zhaoyun",0,1],"7":["zhaoyun_skill_hit",0,1]},"types":["cc.SpriteFrame","cc.Texture2D","sp.SkeletonData","cc.Asset"],"uuids":["05+8fRfWFEK4kfzSiT3dj+","5f6o+JCCxFkLlo7UQn23mw","8fdAsW+HJGhqVT8adsMV+2","91XxGyCEtItrE7WtLrrTUq","9dBNovuzVHX58uFjm9UNwl","feTnGSCnFDVpH354ozYv8M","45yhu9J5JKFLlZRg9rJoDT","58dXIDiPZKPIy+2Iy1P0iX"],"scenes":{},"redirect":[],"deps":[],"packs":{},"name":"zhaoyun","importBase":"import","nativeBase":"native","debug":false,"isZip":false,"encrypted":false,"versions":{"import":[0,"f0473",6,"ebe36",7,"3c58b",1,"f0473",2,"a176c",3,"524e7",4,"9a12e",5,"ca821"],"native":[0,"8b27e",1,"a9233",2,"f83b0",3,"efd5c",4,"849c4",5,"4e9bf"]}}