{"paths":{"0":["ui_room_atlas0_1",3],"1":["livingroom_light",3],"2":["livingroom_light",2],"3":["livingroom_fishtank_water",2],"4":["sdsl_btn",2],"5":["ui_room_atlas0",3],"6":["ygjqr_gzr",3],"7":["ui_btn_kitchen",0],"8":["ui_room",4],"9":["livingroom_fishtank_plants",0],"10":["ygjqr_gzr",2],"11":["livingroom_light",0],"12":["livingroom_fishtank_plants",2],"13":["yuling_1101",0],"14":["yuling_1101",3],"15":["yuling_1503",2],"16":["ui_btn_kitchen",3],"17":["livingroom_fishtank_water",0],"18":["sdsl_btn",0],"19":["ygjqr_gzr",0],"20":["ui_btn_kitchen",2],"21":["livingroom_fishtank_plants",3],"22":["livingroom_fishtank_water",3],"23":["yuling_1503",0],"24":["yuling_1503",3],"25":["yuling_1101",2],"26":["sdsl_btn",3],"27":["yuling_1101",1,1],"28":["ui_room_atlas0",1,1],"29":["ygjqr_gzr",1,1],"30":["ui_room_atlas0_1",1,1],"31":["livingroom_fishtank_water",1,1],"32":["yuling_1503",1,1],"33":["ui_btn_kitchen",1,1],"34":["livingroom_fishtank_plants",1,1],"35":["sdsl_btn",1,1],"36":["livingroom_light",1,1]},"types":["cc.Asset","cc.SpriteFrame","sp.SkeletonData","cc.Texture2D","cc.BufferAsset"],"uuids":["025UNJtZNNI4Ndfj2Vs07N","0eJTjrBJhAqZdLQtYhS/gQ","14sZYL6UNG7qkFvR7oai4O","16Nt8c9DBK3q1lPjjtX6CI","2fGxauFrlHFoFTvNYvwaIu","30uktZwixH9JpA2OWZfKH/","341jTrmRNBVZAmdhQmoKVR","3cBrNU7f9BOpSu4Ybw6Oga","4asvBa55pADJ3GF7LwjeWZ","4fgssgTblE7KLh4gY4cnQP","53/PgEVe9KRKE8cwYLZTd8","5bKlXPV05J7Zk1EEN7w8rt","72AW2Lcn5MMY9Swh79r03I","90Ny9hFKdKKZ6q7+sc27tn","9eJDrCA6VAAKub0PLv+9jl","a4Fck3Q41Ai5Onc9+bjTx8","aaEadHG6ZHPJy78HaDJwu6","aeRUVnXUBHH7tVirGmMe+W","ceO83h+C5CAq1PQqwzxJk5","d2aRt1QDJE35snWVLAkgTB","d32cqPWgVOI4DboUeg4ppi","d4AdfBshBB6qJCnUcBckRl","e1QJzOF75FPJ85AOWKq2lD","edIewiNsBKCZYCPPLfHAh8","fcNbTT0q5KJbNc2ug9j3y0","fcXLtFlEpKaaIRaowvO9gv","ffbv0wxkVMbKXNXe1R5kQU","0csAEO79RCwLZIDudOLHj6","12UV8TCItJ1KyX4J7DDu/T","1bH01xCshJvIjoITVLj8t5","2emJlBt2dFRIs3s/vvV7rZ","35D9+1rBtM2r0eF42zTe5r","58dIjupxJAI7Qt1xxyw6tX","602QNG3zFGcoLRR6SDAzY3","6567JD4zJPx688sJkukfFM","69tfZfDjFLxI75th/iDjmZ","6dODgHHAlMv5Li5WRa58J8"],"scenes":{},"redirect":[],"deps":[],"packs":{},"name":"ui_room","importBase":"import","nativeBase":"native","debug":false,"isZip":false,"encrypted":false,"versions":{"import":[0,"f0473",27,"249d0",1,"f0473",28,"0bcfe",2,"12357",3,"deedf",29,"9e9be",30,"666e4",4,"be80a",5,"f0473",6,"f0473",31,"a9647",7,"16a3b",8,"87285",9,"c7230",10,"ce324",32,"b93d0",11,"d14fc",33,"90cba",34,"dfe28",35,"32bcb",36,"8a423",12,"e3884",13,"a5547",14,"f0473",15,"42f7e",16,"f0473",17,"a4bdf",18,"0cc5e",19,"1c470",20,"2d96f",21,"f0473",22,"f0473",23,"4105a",24,"f0473",25,"17c99",26,"f0473"],"native":[0,"77703",1,"67b34",2,"12a81",3,"26cd0",4,"b4931",5,"e0166",6,"74ca8",7,"111fe",8,"2270c",9,"3e3d6",10,"97393",11,"a4524",12,"3660c",13,"2baab",14,"e63a7",15,"4d9a8",16,"6a1c4",17,"f2615",18,"6c35d",19,"24dcf",20,"a8d73",21,"eb244",22,"b020b",23,"5ce99",24,"5474a",25,"d886e",26,"15639"]}}