{"paths":{"0":["lusu3_skill_position",3],"1":["lusu3_skill_hit",2],"2":["lusu3_attack_hit",2],"3":["lusu3_armor_intro",1],"4":["lusu3",1],"5":["lusu3_armor_intro",2],"6":["lusu3_skill_position",2],"7":["lusu3_skill_position",1],"8":["lusu3_attack_hit",1],"9":["lusu3",2],"10":["lusu3_skill_hit",3],"11":["lusu3_attack_hit",3],"12":["lusu3_skill_hit",1],"13":["lusu3",3],"14":["lusu3_armor_intro",3],"15":["lusu3",0,1],"16":["lusu3_skill_hit",0,1],"17":["lusu3_armor_intro",0,1],"18":["lusu3_skill_position",0,1],"19":["lusu3_attack_hit",0,1]},"types":["cc.SpriteFrame","sp.SkeletonData","cc.Texture2D","cc.Asset"],"uuids":["07PfZ9fYlAb5oK7WCXYr+q","27laW5RIxL1JxY9rpIp+XL","34Nb2PTQtHqYJLx7wfRysf","45800DM+pF3oiYaMtuM2Pa","57CbufwgVIAKOGC4UdYZ7f","5bb4IJO5dPH6oW3C/d/uzV","9d4gBXMktPO5XBKzH5KJQS","a3N0cj6b5HKZ/6wMbJzsP3","b1rsOUUGxIva0uflHCGKQN","banw2knORDq4z5mzqu7KUY","d3FeJzRQVEaZzYLGGkunml","d4c/EEzy1HfLRwFmLKW9Fn","ddYHALqt9F5rlxqz7fRe/t","deaUSUAKlCmoTif7LxHz6s","f89eRctjlDWqhmDoE3FExq","50pfmz1x9FcIbcxHm6pPA8","8fVJ4I9n5KuZWEixEpM5mT","a4VQFWR7hEz6QJaUc0h3Gg","be4jwuTChPj76Sga2GM4KB","d0zZKNERdEaYStbEyJQh9M"],"scenes":{},"redirect":[],"deps":[],"packs":{},"name":"lusu3","importBase":"import","nativeBase":"native","debug":false,"isZip":false,"encrypted":false,"versions":{"import":[0,"cb9a9",1,"f0473",2,"f0473",3,"b5e53",15,"d10e8",4,"df39f",5,"f0473",16,"5529d",6,"f0473",7,"2d084",17,"e2272",8,"87132",9,"f0473",18,"ddd59",19,"485fe",10,"b6cbb",11,"30f73",12,"23715",13,"c8c1c",14,"8b89e"],"native":[0,"b9ef3",1,"c9c70",2,"d2b24",3,"84825",4,"ed676",5,"fbbda",6,"16b6e",7,"351ed",8,"24f74",9,"6ed11",10,"7e1e9",11,"8ea57",12,"4a62c",13,"5263a",14,"29442"]}}